dssex/__init__.py
dssex/_apis.py
dssex/batch.py
dssex/debug.py
dssex/estim.py
dssex/examples.py
dssex/factors.py
dssex/injections.py
dssex/pfcnum.py
dssex/result.py
dssex-0.0.8.dist-info/LICENSE
dssex-0.0.8.dist-info/METADATA
dssex-0.0.8.dist-info/WHEEL
dssex-0.0.8.dist-info/top_level.txt
dssex-0.0.8.dist-info/RECORD
