Metadata-Version: 2.1
Name: dssex
Version: 0.0.8
Summary: Means for experimental State Estimation of electric Distribution Networks
Home-page: https://github.com/pyprg/dssex
Author: pyprg
Author-email: pyprg@outlook.com
Project-URL: Bug Tracker, https://github.com/pyprg/dssex/issues
Classifier: Programming Language :: Python :: 3
Classifier: License :: OSI Approved :: GNU General Public License v3 or later (GPLv3+)
Classifier: Operating System :: OS Independent
Requires-Python: >=3.9
License-File: LICENSE
Requires-Dist: casadi >=3.6.2
Requires-Dist: egrid >=0.0.7
Requires-Dist: numpy >=1.24.3
Requires-Dist: pandas >=2.0.1
Requires-Dist: scipy >=1.10.1
